[
    {
        "name": "Therion",
        "className": "Thief",
        "pathAction": "Steal - allows Therion to steal the belongings of townspeople.",
        "talent": "Pick Lock - allows Therion to open locked treasure chests he encounters in his travels."
    },
    {
        "name": "Primrose",
        "className": "Dancer",
        "pathAction": "Allure - allows Primrose to allure townspeople into following her.",
        "talent": "Summon - allows Primrose to summon a townsperson she has charmed to aid in battle."
    },
    {
        "name": "H'aanit",
        "className": "Hunter",
        "pathAction": "Provoke - allows H'aanit to use beasts to provoke people into battle.",
        "talent": "Capture - allows H'aanit to capture monsters and beasts in battle and train them to fight by her side."
    },
    {
        "name": "Olberic Eisenberg",
        "className": "Warrior",
        "pathAction": "Challenge - allows Olberic to challenge townspeople to a duel.",
        "talent": "Bolster Defense - allows Olberic to boost while defending to protect against the mighty blows of formidable enemies."
    }
]